{
"type": "FeatureCollection",
"name": "Potential DC Fast Chargers",
"crs": { "type": "name", "properties": { "name": "urn:ogc:def:crs:OGC:1.3:CRS84" } },
"features": [
{ "type": "Feature", "properties": { "Name": "Westby" }, "geometry": { "type": "Point", "coordinates": [ -90.855916, 43.6585595 ] } },
{ "type": "Feature", "properties": { "Name": "Viroqua" }, "geometry": { "type": "Point", "coordinates": [ -90.8905492, 43.5724174 ] } }
]
}
